lektor_bibtex_support.py
lektor_bibtex_support-0.1.1.data/data/templates/lektor_bibtex_support_default_template.html
lektor_bibtex_support-0.1.1.dist-info/METADATA
lektor_bibtex_support-0.1.1.dist-info/RECORD
lektor_bibtex_support-0.1.1.dist-info/WHEEL
lektor_bibtex_support-0.1.1.dist-info/entry_points.txt
lektor_bibtex_support-0.1.1.dist-info/top_level.txt
