Metadata-Version: 2.1
Name: lektor-bibtex-support
Version: 0.1.1
Summary: Bibtex file support to easily include publication lists.
Home-page: https://github.com/arunpersaud/lektor-bibtex-support
Author: Arun Persaud
Author-email: arun@nubati.net
License: MIT
Keywords: Lektor plugin static-site bibtex
Platform: UNKNOWN
Classifier: Environment :: Plugins
Classifier: Environment :: Web Environment
Classifier: Framework :: Lektor
Classifier: Intended Audience :: Developers
Classifier: License :: OSI Approved :: MIT License
Classifier: Programming Language :: Python :: 3.6
Classifier: Programming Language :: Python :: 3.7
Requires-Dist: pybtex
